dropbox/__init__.py
dropbox/api_helper.py
dropbox/configuration.py
dropbox/dropbox_client.py
dropbox/controllers/__init__.py
dropbox/controllers/base_controller.py
dropbox/controllers/files_controller.py
dropbox/controllers/o_auth_authorization_controller.py
dropbox/exceptions/__init__.py
dropbox/exceptions/api_exception.py
dropbox/exceptions/o_auth_provider_exception.py
dropbox/http/__init__.py
dropbox/http/http_call_back.py
dropbox/http/http_method_enum.py
dropbox/http/http_request.py
dropbox/http/http_response.py
dropbox/http/auth/__init__.py
dropbox/http/auth/o_auth_2.py
dropbox/models/__init__.py
dropbox/models/o_auth_provider_error_enum.py
dropbox/models/o_auth_token.py
dropbox/models/response.py
dropbox/utilities/__init__.py
dropbox/utilities/file_wrapper.py
dropbox_sdk-1.0.0.dist-info/licenses/LICENSE
dropbox_sdk-1.0.0.dist-info/METADATA
dropbox_sdk-1.0.0.dist-info/WHEEL
dropbox_sdk-1.0.0.dist-info/top_level.txt
dropbox_sdk-1.0.0.dist-info/RECORD
